{
    "db": [
        { "relations": ["T0"], "size": 909},
        { "relations": ["T1"], "size": 812},
        { "relations": ["T2"], "size": 44},
        { "relations": ["T3"], "size": 204},
        { "relations": ["T4"], "size": 12},
        { "relations": ["T5"], "size": 59},
        { "relations": ["T6"], "size": 28},
        { "relations": ["T7"], "size": 664},
        { "relations": ["T8"], "size": 20},
        { "relations": ["T9"], "size": 43},
        { "relations": ["T0", "T1", "T2", "T4", "T5", "T6", "T7", "T8", "T9"], "size": 16432},
        { "relations": ["T0", "T1", "T2", "T4", "T5", "T6", "T9"], "size": 80525},
        { "relations": ["T0", "T1", "T2", "T3", "T4", "T5", "T6", "T7", "T8", "T9"], "size": 128},
        { "relations": ["T0", "T1", "T3", "T4", "T5", "T6", "T7", "T8", "T9"], "size": 2467570},
        { "relations": ["T0", "T1", "T2", "T3", "T5", "T6", "T7", "T9"], "size": 10781},
        { "relations": ["T0", "T1", "T3", "T5", "T6", "T7", "T8", "T9"], "size": 4783740},
        { "relations": ["T0", "T1", "T3", "T5", "T6", "T7", "T9"], "size": 7457188},
        { "relations": ["T0", "T1", "T2", "T4", "T5", "T6", "T7", "T9"], "size": 25616},
        { "relations": ["T0", "T1", "T2", "T3", "T4", "T5", "T6", "T8", "T9"], "size": 29839},
        { "relations": ["T0", "T1", "T2", "T3", "T4", "T5", "T6", "T9"], "size": 46515},
        { "relations": ["T0", "T2", "T3", "T4", "T5", "T6", "T7", "T8", "T9"], "size": 18897},
        { "relations": ["T0", "T2", "T3", "T4", "T5", "T6", "T7", "T9"], "size": 29459},
        { "relations": ["T0", "T2", "T3", "T5", "T6", "T7", "T8", "T9"], "size": 1013709},
        { "relations": ["T0", "T3", "T5", "T6", "T7", "T8", "T9"], "size": 19063416},
        { "relations": ["T0", "T2", "T3", "T4", "T5", "T6", "T8", "T9"], "size": 49341},
        { "relations": ["T0", "T3", "T4", "T5", "T6", "T8", "T9"], "size": 1090318},
        { "relations": ["T0", "T2", "T3", "T5", "T6", "T8", "T9"], "size": 2646752},
        { "relations": ["T0", "T1", "T3", "T4", "T8", "T9"], "size": 4458912},
        { "relations": ["T0", "T1", "T5", "T6", "T7", "T8", "T9"], "size": 745855},
        { "relations": ["T0", "T1", "T2", "T3", "T4", "T6", "T7", "T8", "T9"], "size": 62},
        { "relations": ["T0", "T1", "T3", "T4", "T6", "T7", "T8", "T9"], "size": 1200652},
        { "relations": ["T0", "T1", "T2", "T3", "T6", "T8", "T9"], "size": 778821},
        { "relations": ["T0", "T2", "T3", "T4", "T6", "T7", "T8", "T9"], "size": 9195},
        { "relations": ["T0", "T2", "T3", "T4", "T6", "T8", "T9"], "size": 24008},
        { "relations": ["T0", "T2", "T3", "T6", "T7", "T8", "T9"], "size": 493243},
        { "relations": ["T0", "T3", "T4", "T6", "T8", "T9"], "size": 530519},
        { "relations": ["T0", "T1", "T2", "T4", "T6", "T8", "T9"], "size": 25102},
        { "relations": ["T0", "T1", "T3", "T4", "T7", "T8", "T9"], "size": 453675},
        { "relations": ["T0", "T1", "T2", "T3", "T7", "T8", "T9"], "size": 1271},
        { "relations": ["T0", "T1", "T3", "T7", "T8", "T9"], "size": 879515},
        { "relations": ["T0", "T3", "T4", "T7", "T8", "T9"], "size": 1807916},
        { "relations": ["T0", "T3", "T7", "T8", "T9"], "size": 3504907},
        { "relations": ["T0", "T1", "T2", "T3", "T6", "T7", "T8", "T9"], "size": 3365},
        { "relations": ["T0", "T1", "T7", "T8", "T9"], "size": 137128},
        { "relations": ["T0", "T1", "T2", "T8", "T9"], "size": 21898},
        { "relations": ["T0", "T1", "T3", "T4", "T6", "T7", "T9"], "size": 1873984},
        { "relations": ["T0", "T1", "T2", "T3", "T6", "T7", "T9"], "size": 5252},
        { "relations": ["T0", "T1", "T3", "T6", "T7", "T9"], "size": 3632989},
        { "relations": ["T0", "T1", "T2", "T6", "T7", "T8", "T9"], "size": 18436},
        { "relations": ["T0", "T1", "T2", "T3", "T4", "T6", "T9"], "size": 22604},
        { "relations": ["T0", "T1", "T2", "T3", "T6", "T9"], "size": 1215037},
        { "relations": ["T0", "T1", "T3", "T6", "T7", "T8", "T9"], "size": 2327637},
        { "relations": ["T0", "T2", "T3", "T4", "T6", "T7", "T9"], "size": 14351},
        { "relations": ["T0", "T1", "T2", "T3", "T5", "T6", "T8", "T9"], "size": 1600626},
        { "relations": ["T0", "T3", "T4", "T6", "T7", "T9"], "size": 7467922},
        { "relations": ["T0", "T3", "T4", "T6", "T9"], "size": 827663},
        { "relations": ["T0", "T2", "T3", "T6", "T9"], "size": 2009154},
        { "relations": ["T0", "T1", "T2", "T4", "T6", "T9"], "size": 39133},
        { "relations": ["T0", "T1", "T3", "T4", "T6", "T9"], "size": 18409974},
        { "relations": ["T0", "T1", "T2", "T3", "T4", "T7", "T8", "T9"], "size": 23},
        { "relations": ["T0", "T1", "T2", "T6", "T7", "T9"], "size": 28762},
        { "relations": ["T0", "T1", "T6", "T7", "T9"], "size": 566163},
        { "relations": ["T1", "T2", "T7", "T9"], "size": 363},
        { "relations": ["T0", "T3", "T6", "T7", "T9"], "size": 14477644},
        { "relations": ["T0", "T1", "T2", "T3", "T4", "T5", "T6", "T7", "T9"], "size": 200},
        { "relations": ["T0", "T3", "T6", "T8", "T9"], "size": 1028488},
        { "relations": ["T0", "T1", "T5", "T6", "T8", "T9"], "size": 99568},
        { "relations": ["T0", "T1", "T3", "T4", "T5", "T6", "T9"], "size": 37806006},
        { "relations": ["T0", "T1", "T2", "T5", "T6", "T7", "T8", "T9"], "size": 37890},
        { "relations": ["T0", "T5", "T6", "T8"], "size": 3166},
        { "relations": ["T0", "T1", "T3", "T4", "T7", "T9"], "size": 708099},
        { "relations": ["T0", "T3", "T8", "T9"], "size": 388622},
        { "relations": ["T0", "T1", "T2", "T3", "T4", "T6", "T8", "T9"], "size": 14499},
        { "relations": ["T1", "T2"], "size": 971},
        { "relations": ["T0", "T2", "T3", "T4", "T8", "T9"], "size": 9071},
        { "relations": ["T0", "T2", "T3", "T7", "T9"], "size": 290896},
        { "relations": ["T1", "T2", "T3"], "size": 5629},
        { "relations": ["T0", "T1", "T6", "T7", "T8", "T9"], "size": 362909},
        { "relations": ["T2", "T4"], "size": 19},
        { "relations": ["T1", "T2", "T4"], "size": 419},
        { "relations": ["T3", "T4"], "size": 105},
        { "relations": ["T2", "T3", "T4"], "size": 4},
        { "relations": ["T0", "T8", "T9"], "size": 823},
        { "relations": ["T0", "T1", "T2", "T3", "T4", "T8", "T9"], "size": 5478},
        { "relations": ["T0", "T6"], "size": 2405},
        { "relations": ["T0", "T2", "T3", "T6", "T7", "T9"], "size": 769858},
        { "relations": ["T5", "T6"], "size": 57},
        { "relations": ["T0", "T5", "T6"], "size": 4897},
        { "relations": ["T1", "T7"], "size": 6082},
        { "relations": ["T2", "T7"], "size": 1240},
        { "relations": ["T1", "T2", "T7"], "size": 308},
        { "relations": ["T0", "T1", "T3", "T4", "T6", "T8", "T9"], "size": 11800516},
        { "relations": ["T1", "T2", "T3", "T7"], "size": 24},
        { "relations": ["T0", "T3", "T4", "T5", "T6", "T7", "T8", "T9"], "size": 9833376},
        { "relations": ["T0", "T2", "T3", "T6", "T8", "T9"], "size": 1287837},
        { "relations": ["T1", "T3", "T4", "T7"], "size": 8684},
        { "relations": ["T0", "T1", "T2", "T7", "T8", "T9"], "size": 6966},
        { "relations": ["T2", "T4", "T7"], "size": 537},
        { "relations": ["T0", "T6", "T8"], "size": 1542},
        { "relations": ["T3", "T9"], "size": 20304},
        { "relations": ["T3", "T7"], "size": 1839},
        { "relations": ["T0", "T1", "T2", "T4", "T7", "T8", "T9"], "size": 3017},
        { "relations": ["T2", "T3", "T7"], "size": 97},
        { "relations": ["T0", "T3", "T4", "T5", "T6", "T7", "T9"], "size": 15328876},
        { "relations": ["T3", "T4", "T7"], "size": 948},
        { "relations": ["T2", "T3", "T4", "T7"], "size": 1},
        { "relations": ["T0", "T1", "T2", "T5", "T6", "T9"], "size": 185676},
        { "relations": ["T1", "T3", "T7"], "size": 16846},
        { "relations": ["T2", "T3"], "size": 255},
        { "relations": ["T0", "T5", "T6", "T8", "T9"], "size": 4476},
        { "relations": ["T0", "T3", "T5", "T6", "T7", "T9"], "size": 29717236},
        { "relations": ["T0", "T1", "T2", "T3", "T4", "T6", "T7", "T9"], "size": 97},
        { "relations": ["T1", "T3", "T9"], "size": 451628},
        { "relations": ["T1", "T2", "T3", "T4", "T7"], "size": 1},
        { "relations": ["T0", "T6", "T9"], "size": 3398},
        { "relations": ["T0", "T1", "T2", "T6", "T8", "T9"], "size": 57954},
        { "relations": ["T1", "T3", "T4", "T9"], "size": 232954},
        { "relations": ["T0", "T6", "T8", "T9"], "size": 2178},
        { "relations": ["T0", "T5", "T6", "T9"], "size": 6978},
        { "relations": ["T0", "T2", "T3", "T5", "T6", "T9"], "size": 4125921},
        { "relations": ["T1", "T2", "T3", "T4"], "size": 104},
        { "relations": ["T0", "T1", "T3", "T8", "T9"], "size": 8644244},
        { "relations": ["T1", "T9"], "size": 956},
        { "relations": ["T1", "T2", "T9"], "size": 1143},
        { "relations": ["T0", "T1", "T3", "T4", "T5", "T6", "T8", "T9"], "size": 24252320},
        { "relations": ["T2", "T3", "T4", "T7", "T9"], "size": 181},
        { "relations": ["T1", "T7", "T9"], "size": 7161},
        { "relations": ["T0", "T1", "T9"], "size": 28559},
        { "relations": ["T1", "T2", "T4", "T9"], "size": 495},
        { "relations": ["T0", "T2", "T3", "T7", "T8", "T9"], "size": 186375},
        { "relations": ["T0", "T1", "T2", "T3", "T9"], "size": 459286},
        { "relations": ["T0", "T1", "T2", "T3", "T5", "T6", "T9"], "size": 2495154},
        { "relations": ["T0", "T1", "T5", "T6", "T7", "T9"], "size": 1162688},
        { "relations": ["T1", "T2", "T4", "T7", "T9"], "size": 157},
        { "relations": ["T1", "T3", "T4", "T7", "T9"], "size": 23702},
        { "relations": ["T0", "T1", "T2", "T4", "T9"], "size": 14787},
        { "relations": ["T0", "T2", "T3", "T4", "T5", "T6", "T9"], "size": 76916},
        { "relations": ["T2", "T3", "T9"], "size": 25423},
        { "relations": ["T0", "T3", "T9"], "size": 606567},
        { "relations": ["T3", "T4", "T9"], "size": 10473},
        { "relations": ["T2", "T3", "T4", "T9"], "size": 473},
        { "relations": ["T0", "T1", "T2", "T3", "T4", "T7", "T9"], "size": 36},
        { "relations": ["T0", "T1", "T2", "T5", "T6", "T7", "T9"], "size": 59066},
        { "relations": ["T0", "T3", "T6", "T7", "T8", "T9"], "size": 9275740},
        { "relations": ["T0", "T1", "T3", "T4", "T9"], "size": 6959329},
        { "relations": ["T0", "T3", "T4", "T7", "T9"], "size": 2821809},
        { "relations": ["T2", "T3", "T7", "T9"], "size": 9737},
        { "relations": ["T0", "T3", "T4", "T8", "T9"], "size": 200460},
        { "relations": ["T0", "T1", "T2", "T4", "T8", "T9"], "size": 9485},
        { "relations": ["T3", "T7", "T9"], "size": 183117},
        { "relations": ["T3", "T4", "T7", "T9"], "size": 94456},
        { "relations": ["T0", "T3", "T4", "T6", "T7", "T8", "T9"], "size": 4784653},
        { "relations": ["T0", "T3", "T4", "T9"], "size": 312873},
        { "relations": ["T1", "T2", "T3", "T4", "T9"], "size": 285},
        { "relations": ["T1", "T3", "T7", "T9"], "size": 45951},
        { "relations": ["T0", "T2", "T3", "T8", "T9"], "size": 486619},
        { "relations": ["T1", "T2", "T4", "T7"], "size": 133},
        { "relations": ["T0", "T1", "T3", "T5", "T6", "T8", "T9"], "size": 47016617},
        { "relations": ["T1", "T2", "T3", "T7", "T9"], "size": 66},
        { "relations": ["T0", "T3", "T4", "T5", "T6", "T9"], "size": 1699656},
        { "relations": ["T1", "T2", "T3", "T4", "T7", "T9"], "size": 1},
        { "relations": ["T0", "T2", "T3", "T4", "T7", "T8", "T9"], "size": 3474},
        { "relations": ["T0", "T1", "T2", "T9"], "size": 34146},
        { "relations": ["T0", "T1", "T7", "T9"], "size": 213929},
        { "relations": ["T0", "T1", "T2", "T7", "T9"], "size": 10868},
        { "relations": ["T0", "T1", "T2", "T5", "T6", "T8", "T9"], "size": 119110},
        { "relations": ["T0", "T9"], "size": 1284},
        { "relations": ["T0", "T1", "T2", "T4", "T7", "T9"], "size": 4703},
        { "relations": ["T0", "T2", "T3", "T9"], "size": 759493},
        { "relations": ["T0", "T2", "T3", "T4", "T9"], "size": 14158},
        { "relations": ["T0", "T3", "T7", "T9"], "size": 5470485},
        { "relations": ["T0", "T2", "T3", "T4", "T7", "T9"], "size": 5422},
        { "relations": ["T0", "T1", "T2", "T4", "T5", "T6", "T8", "T9"], "size": 51656},
        { "relations": ["T0", "T1", "T2", "T3", "T4", "T9"], "size": 8541},
        { "relations": ["T0", "T1", "T2", "T3", "T7", "T9"], "size": 1984},
        { "relations": ["T0", "T1", "T5", "T6", "T9"], "size": 155213},
        { "relations": ["T0", "T1", "T6", "T9"], "size": 75582},
        { "relations": ["T0", "T1", "T2", "T4", "T6", "T7", "T9"], "size": 12446},
        { "relations": ["T1", "T2", "T3", "T9"], "size": 15374},
        { "relations": ["T0", "T1", "T2", "T6", "T9"], "size": 90416},
        { "relations": ["T0", "T1", "T3", "T7", "T9"], "size": 1372752},
        { "relations": ["T0", "T1", "T8", "T9"], "size": 18306},
        { "relations": ["T0", "T1", "T2", "T3", "T5", "T6", "T7", "T8", "T9"], "size": 6916},
        { "relations": ["T0", "T3", "T5", "T6", "T8", "T9"], "size": 2113740},
        { "relations": ["T0", "T1", "T6", "T8", "T9"], "size": 48446},
        { "relations": ["T0", "T1", "T3", "T9"], "size": 13492054},
        { "relations": ["T0", "T1", "T2", "T4", "T6", "T7", "T8", "T9"], "size": 7984},
        { "relations": ["T0", "T2", "T3", "T4", "T6", "T9"], "size": 37455},
        { "relations": ["T0", "T3", "T6", "T9"], "size": 1604544},
        { "relations": ["T0", "T8"], "size": 583},
        { "relations": ["T0", "T3", "T5", "T6", "T9"], "size": 3295029},
        { "relations": ["T0", "T1", "T2", "T3", "T8", "T9"], "size": 294283},
        { "relations": ["T0", "T1", "T3", "T6", "T9"], "size": 35690388},
        { "relations": ["T0", "T1", "T3", "T6", "T8", "T9"], "size": 22877001},
        { "relations": ["T0", "T1", "T3", "T4", "T5", "T6", "T7", "T9"], "size": 3846599},
        { "relations": ["T0", "T2", "T3", "T5", "T6", "T7", "T9"], "size": 1580233},
        { "relations": ["T0", "T1", "T3", "T5", "T6", "T9"], "size": 73292390}
    ]
}
